README.md
setup.cfg
setup.py
jr_dsnd_probability/Binomialdistribution.py
jr_dsnd_probability/Gaussiandistribution.py
jr_dsnd_probability/Generaldistribution.py
jr_dsnd_probability/__init__.py
jr_dsnd_probability.egg-info/PKG-INFO
jr_dsnd_probability.egg-info/SOURCES.txt
jr_dsnd_probability.egg-info/dependency_links.txt
jr_dsnd_probability.egg-info/not-zip-safe
jr_dsnd_probability.egg-info/top_level.txt