Metadata-Version: 1.0
Name: jr-dsnd-probability
Version: 1.0
Summary: Gaussian and Binomial distributions
Home-page: UNKNOWN
Author: Jawad Rashid
Author-email: info@ndataconsulting.com
License: UNKNOWN
Platform: UNKNOWN
